{
  "EI": [
    {"question": "🤔 在课堂讨论中，我更喜欢主动发言。", "score": "E"},
    {"question": "🤔 我在社交活动后，会感到开心。", "score": "E"},
    {"question": "🤔 我在活动中更愿意承担领导角色。", "score": "E"},
    {"question": "🤔 我喜欢在课间休息时与同学们一起聊天。", "score": "E"},
    {"question": "🤔 在大型活动中我通常会感到兴奋和有活力，比如运动会。", "score": "E"},
    {"question": "🤔 在考试前，我通常会选择一个安静的地方来集中复习。", "score": "I"},
    {"question": "🤔 我在完成作业时更喜欢一个安静的环境。", "score": "I"},
    {"question": "🤔 我更喜欢独自复习，因为我可以专注并按照自己的步调进行。", "score": "I"},
    {"question": "🤔 我很擅长处理朋友之间的冲突。", "score": "E"},
	  {"question": "🤔 我更愿意将时间花研究喜欢的事，而不是社交活动上。", "score": "I"}, 
	  {"question": "🤔 当遇到新的人和新的环境时，我很少感到有些不自在。", "score": "E"}, 
	  {"question": "🤔 来到新的班级或者环境，我能很快适应。", "score": "E"}, 
    {"question": "🤔 我喜欢和其他人一起复习，因为互相讨论可以帮助我理解。", "score": "E"},
	  {"question": "🤔 我享受与他人分享自己的经历和观点。", "score": "E"}
  ],
  "SN": [
    {"question": "😳 我更喜欢通过实践学习新事物，而不是书本。", "score": "S"},
	  {"question": "😳 我倾向于使用已经证明有效的方法，而不是创新的方法。", "score": "S"}, 
    {"question": "😳 我喜欢详细规划我每天的学习任务。", "score": "S"},
    {"question": "😳 我更倾向于根据书本和教师的指示来学习。", "score": "S"},
    {"question": "😳 我很擅长理论和抽象概念的学科，比如数学物理。", "score": "N"},
    {"question": "😳 在学习时，我更愿意先理解大局再去研究细节。", "score": "N"},
    {"question": "😳 我经常在想象未来自己的职业会是什么样的。", "score": "N"},
    {"question": "😳 我喜欢尝试新的学习方法，看看是否更适合我。", "score": "N"},
    {"question": "😳 我通常会因为兴趣，而不是因为必须要学习，去探索新的知识。", "score": "N"},
    {"question": "😳 我更喜欢通过历年试题和模拟考试来复习，而不是在理解概念和理论的基础上进行复习。", "score": "S"}
  ],
  "TF": [
	  {"question": "🤥 在面对问题时，我倾向于理性地分析问题，而非依赖情绪。", "score": "T"},
    {"question": "🤥 我喜欢直截了当地解决问题，而不是过多考虑他人的感受。", "score": "T"},
    {"question": "🤥 我喜欢依据规则和标准来评判自己的行为。", "score": "T"},
    {"question": "🤥 我通常用逻辑和理性来决定是否信任他人的观点。", "score": "T"},
    {"question": "🤥 在学习或完成任务时，我更重视效率而不是过程。", "score": "T"},
    {"question": "🤥 我善于理解和关心他人的感受。", "score": "F"},
    {"question": "🤥 在团队项目中，我通常会考虑每个成员的感受。", "score": "F"},
    {"question": "🤥 我善于理解和解释文学作品中的情感和价值。", "score": "F"},
    {"question": "🤥 我认为理解和表达自己的感受是很重要的。", "score": "F"},
    {"question": "🤥 我将复习重点放在我最需要提高的地方，以提高我的总分。", "score": "T"},
    {"question": "🤥 在选择复习的内容时，我会根据分值来决定先复习哪些。", "score": "T"},
	  {"question": "🤥 我认为'效率和结果'比'过程和感觉'更重要。", "score": "T"},
    {"question": "🤥 我会花时间考虑老师在出这个题目时可能的想法和目的。", "score": "F"}
  ],
  "JP": [
    {"question": "😬 我喜欢在开始一项任务前制定计划。", "score": "J"},
    {"question": "😬 我倾向于按照预定的时间表来学习。", "score": "J"},
    {"question": "😬 我喜欢完成任务后的满足感。", "score": "J"},
    {"question": "😬 我喜欢事先知道老师的期望和评分标准。", "score": "J"},
    {"question": "😬 我更喜欢提前复习，以便有足够的时间来准备。", "score": "J"},
	  {"question": "😬 我喜欢事先做好计划，按照计划行事，不喜欢临时变动。", "score": "J"},
	  {"question": "😬 我倾向于提前做决策，不喜欢拖延。", "score": "J"},
    {"question": "😬 我喜欢在没有压力的情况下自由地学习。", "score": "P"},
    {"question": "😬 我喜欢在项目进行中调整和改变计划。", "score": "P"},
    {"question": "😬 我喜欢在做决定时有很多选项可以选择。", "score": "P"},
    {"question": "😬 我通常会在最后一刻完成作业。", "score": "P"},
    {"question": "😬 我在复习考试时喜欢按照自己的步调，而不是严格的时间表。", "score": "P"}
  ]
}

